[
    {
        "id": "10-e40c0f23",
        "name": "Anon",
        "undergraduate": true
    },
    {
        "id": "11-e40c0f23",
        "name": "Anon",
        "undergraduate": true
    },
    {
        "id": "13-696e641c",
        "name": "Anon",
        "undergraduate": false
    },
    {
        "id": "6-442464cd",
        "name": "Anon",
        "undergraduate": true
    },
    {
        "id": "7-575fd418",
        "name": "Anon",
        "undergraduate": true
    },
    {
        "id": "14-e7b22f72",
        "name": "Anon",
        "undergraduate": false
    },
    {
        "id": "15-8528e23b",
        "name": "Anon",
        "undergraduate": false
    },
    {
        "id": "2-71043342",
        "name": "Anon",
        "undergraduate": true
    },
    {
        "id": "3-e6c6b843",
        "name": "Anon",
        "undergraduate": false
    },
    {
        "id": "1-f7079988",
        "name": "Anon",
        "undergraduate": true
    },
    {
        "id": "8-0126226f",
        "name": "Anon",
        "undergraduate": false
    },
    {
        "id": "4-625bf89a",
        "name": "Anon",
        "undergraduate": false
    },
    {
        "id": "5-bd4e6d25",
        "name": "Anon",
        "undergraduate": false
    },
    {
        "id": "9-981fed75",
        "name": "Anon",
        "undergraduate": false
    },
    {
        "id": "12-319c988d",
        "name": "Anon",
        "undergraduate": false
    },
    {
        "id": "16-3b2bf65e",
        "name": "Anon",
        "undergraduate": true
    },
    {
        "id": "17-a8b684de",
        "name": "Anon",
        "undergraduate": true
    }
]